setup.py
lib/evasion/__init__.py
lib/evasion/agency/__init__.py
lib/evasion/agency/agency.py
lib/evasion/agency/agent.py
lib/evasion/agency/manager.py
lib/evasion/agency/utils.py
lib/evasion/agency/agents/__init__.py
lib/evasion/agency/agents/base/__init__.py
lib/evasion/agency/agents/base/service.py
lib/evasion/agency/agents/testing/__init__.py
lib/evasion/agency/agents/testing/fake.py
lib/evasion/agency/agents/testing/resttest.py
lib/evasion/agency/agents/tests/__init__.py
lib/evasion/agency/tests/__init__.py
lib/evasion/agency/tests/testagency.py
lib/evasion/director/__init__.py
lib/evasion/director/config.py
lib/evasion/director/configobjs.py
lib/evasion/director/lockabledict.py
lib/evasion/director/manager.py
lib/evasion/director/morbid.py
lib/evasion/director/proxydispatch.py
lib/evasion/director/signals.py
lib/evasion/director/testing.py
lib/evasion/director/utils.py
lib/evasion/director/viewpointcontrol.py
lib/evasion/director/viewpointdirect.py
lib/evasion/director/controllers/__init__.py
lib/evasion/director/controllers/agencyctrl.py
lib/evasion/director/controllers/base.py
lib/evasion/director/controllers/commandline.py
lib/evasion/director/controllers/viewpoint.py
lib/evasion/director/controllers/viewpointpassive.py
lib/evasion/director/controllers/viewpointxulcontrol.py
lib/evasion/director/controllers/webadminctrl.py
lib/evasion/director/docs/__init__.py
lib/evasion/director/scripts/__init__.py
lib/evasion/director/scripts/main.py
lib/evasion/director/templatecfg/__init__.py
lib/evasion/director/tests/__init__.py
lib/evasion/director/tests/testdirector.py
lib/evasion/director/tests/testdirectorconfig.py
lib/evasion/director/tests/testlockabledict.py
lib/evasion/director/tools/__init__.py
lib/evasion/director/tools/net.py
lib/evasion/director/tools/proc.py
lib/evasion_director.egg-info/PKG-INFO
lib/evasion_director.egg-info/SOURCES.txt
lib/evasion_director.egg-info/dependency_links.txt
lib/evasion_director.egg-info/eager_resources.txt
lib/evasion_director.egg-info/entry_points.txt
lib/evasion_director.egg-info/namespace_packages.txt
lib/evasion_director.egg-info/not-zip-safe
lib/evasion_director.egg-info/requires.txt
lib/evasion_director.egg-info/top_level.txt
scripts/director
scripts/morbidsvr