Metadata-Version: 1.0
Name: evasion-director
Version: 1.1.6
Summary: Evasion Project
